qubosolver/__init__.py
qubosolver/config.py
qubosolver/data.py
qubosolver/data_utils.py
qubosolver/main.py
qubosolver/qubo_analyzer.py
qubosolver/qubo_instance.py
qubosolver/qubo_types.py
qubosolver/saveload.py
qubosolver/solver.py
qubosolver/algorithms/__init__.py
qubosolver/algorithms/blade/__init__.py
qubosolver/algorithms/blade/_dimension_shrinker.py
qubosolver/algorithms/blade/_dist_constraints_forces.py
qubosolver/algorithms/blade/_distances_constraints_calculator.py
qubosolver/algorithms/blade/_force.py
qubosolver/algorithms/blade/_helpers.py
qubosolver/algorithms/blade/_interactions_forces.py
qubosolver/algorithms/blade/_qubo_mapper.py
qubosolver/algorithms/blade/blade.py
qubosolver/algorithms/blade/drawing.py
qubosolver/algorithms/greedy/__init__.py
qubosolver/algorithms/greedy/greedy.py
qubosolver/classical_solver/__init__.py
qubosolver/classical_solver/classical_solver.py
qubosolver/classical_solver/classical_solver_conversion_tools.py
qubosolver/classical_solver/simulated_annealing.py
qubosolver/classical_solver/tabu_search.py
qubosolver/pipeline/__init__.py
qubosolver/pipeline/basesolver.py
qubosolver/pipeline/drive.py
qubosolver/pipeline/embedder.py
qubosolver/pipeline/fixtures.py
qubosolver/pipeline/waveforms.py
qubosolver/utils/__init__.py
qubosolver/utils/density.py
qubosolver/utils/qubo_eval.py
qubo_solver-0.3.0.dist-info/METADATA
qubo_solver-0.3.0.dist-info/WHEEL
qubo_solver-0.3.0.dist-info/licenses/LICENSE
qubo_solver-0.3.0.dist-info/RECORD
