Metadata-Version: 2.4
Name: qubo-solver
Version: 0.3.0
Summary: A Quadratic Unconstrained Binary Optimization (QUBO) solver library using quantum and classical approaches.
Project-URL: Documentation, https://pasqal-io.github.io/qubo-solver/latest/
Project-URL: Issues, https://github.com/pasqal-io/qubo-solver/issues
Project-URL: Source, https://github.com/pasqal-io/qubo-solver
Author-email: Manu Lahariya <manu.lahariya@pasqal.com>, Charles Moussa <c.moussa@pasqal.com>, Yassine Naghmouchi <yassine.naghmouchi@pasqal.com>, Quentin Ma <quentin.ma@pasqal.com>, Monique Garzillo <monique.garzillo@pasqal.com>, Daniele Cucurachi <daniele.cucurachi@pasqal.com>, Clément de Terrasson de Montleau <clement.de-terrasson@pasqal.com>
License: MIT-derived
License-File: LICENSE
Keywords: combinatorial,optimization,quantum,qubo,solver
Classifier: Development Status :: 4 - Beta
Classifier: Programming Language :: Python
Classifier: Programming Language :: Python :: 3.10
Classifier: Programming Language :: Python :: 3.11
Classifier: Programming Language :: Python :: 3.12
Classifier: Programming Language :: Python :: Implementation :: CPython
Classifier: Programming Language :: Python :: Implementation :: PyPy
Requires-Python: <3.13,>=3.10
Requires-Dist: cplex
Requires-Dist: numpy
Requires-Dist: pandas
Requires-Dist: pydantic>=2
Requires-Dist: pymaxflow
Requires-Dist: qoolqit[solvers]==0.3.0
Requires-Dist: scikit-learn
Requires-Dist: scikit-optimize
Requires-Dist: seaborn
Requires-Dist: torch
Provides-Extra: extras
Requires-Dist: jupyter; extra == 'extras'
Requires-Dist: tqdm; extra == 'extras'
